{"time":{"updated":"Aug 1, 2022 23:21:00 UTC","updatedISO":"2022-08-01T23:21:00+00:00","updateduk":"Aug 2, 2022 at 00:21 BST"},"disclaimer":"This data was produced from the CoinDesk Bitcoin Price Index (USD). Non-USD currency data converted using hourly conversion rate from openexchangerates.org","chartName":"Bitcoin","bpi":{"USD":{"code":"USD","symbol":"&#36;","rate":"23,325.1281","description":"United States Dollar","rate_float":23325.1281},"GBP":{"code":"GBP","symbol":"&pound;","rate":"19,490.2904","description":"British Pound Sterling","rate_float":19490.2904},"EUR":{"code":"EUR","symbol":"&euro;","rate":"22,722.0802","description":"Euro","rate_float":22722.0802},"CNY":{"code":"CNY","symbol":"&yen;","rate":"40,202.5000","description":"Chinese Yuan","rate_float":40202.5}}}