{"time":{"updated":"Jun 16, 2024 23:20:45 UTC","updatedISO":"2024-06-16T23:20:45+00:00","updateduk":"Jun 17, 2024 at 00:20 BST"},"disclaimer":"This data was produced from the CoinDesk Bitcoin Price Index (USD). Non-USD currency data converted using hourly conversion rate from openexchangerates.org","chartName":"Bitcoin","bpi":{"USD":{"code":"USD","symbol":"&#36;","rate":"66,641.234","description":"United States Dollar","rate_float":66641.2342},"GBP":{"code":"GBP","symbol":"&pound;","rate":"52,525.355","description":"British Pound Sterling","rate_float":52525.3546},"EUR":{"code":"EUR","symbol":"&euro;","rate":"62,241.647","description":"Euro","rate_float":62241.6465},"CNY":{"code":"CNY","symbol":"&yen;","rate":"473,839.167","description":"Chinese Yuan","rate_float":473839.1672}}}