{"time":{"updated":"Nov 29, 2024 08:28:28 UTC","updatedISO":"2024-11-29T08:28:28+00:00","updateduk":"Nov 29, 2024 at 08:28 GMT"},"disclaimer":"This data was produced from the CoinDesk Bitcoin Price Index (USD). Non-USD currency data converted using hourly conversion rate from openexchangerates.org","chartName":"Bitcoin","bpi":{"USD":{"code":"USD","symbol":"&#36;","rate":"95,962.299","description":"United States Dollar","rate_float":95962.2994},"GBP":{"code":"GBP","symbol":"&pound;","rate":"75,425.504","description":"British Pound Sterling","rate_float":75425.5036},"EUR":{"code":"EUR","symbol":"&euro;","rate":"90,703.278","description":"Euro","rate_float":90703.2775},"CNY":{"code":"CNY","symbol":"&yen;","rate":"693,586.711","description":"Chinese Yuan","rate_float":693586.7111}}}