{"time":{"updated":"Nov 10, 2024 15:21:58 UTC","updatedISO":"2024-11-10T15:21:58+00:00","updateduk":"Nov 10, 2024 at 15:21 GMT"},"disclaimer":"This data was produced from the CoinDesk Bitcoin Price Index (USD). Non-USD currency data converted using hourly conversion rate from openexchangerates.org","chartName":"Bitcoin","bpi":{"USD":{"code":"USD","symbol":"&#36;","rate":"79,589.168","description":"United States Dollar","rate_float":79589.1684},"GBP":{"code":"GBP","symbol":"&pound;","rate":"61,613.477","description":"British Pound Sterling","rate_float":61613.4772},"EUR":{"code":"EUR","symbol":"&euro;","rate":"74,253.988","description":"Euro","rate_float":74253.9881},"CNY":{"code":"CNY","symbol":"&yen;","rate":"571,386.558","description":"Chinese Yuan","rate_float":571386.5576}}}