{"time":{"updated":"Oct 14, 2023 11:42:00 UTC","updatedISO":"2023-10-14T11:42:00+00:00","updateduk":"Oct 14, 2023 at 12:42 BST"},"disclaimer":"This data was produced from the CoinDesk Bitcoin Price Index (USD). Non-USD currency data converted using hourly conversion rate from openexchangerates.org","chartName":"Bitcoin","bpi":{"USD":{"code":"USD","symbol":"&#36;","rate":"26,867.9499","description":"United States Dollar","rate_float":26867.9499},"GBP":{"code":"GBP","symbol":"&pound;","rate":"22,450.6440","description":"British Pound Sterling","rate_float":22450.644},"EUR":{"code":"EUR","symbol":"&euro;","rate":"26,173.3060","description":"Euro","rate_float":26173.306},"CNY":{"code":"CNY","symbol":"&yen;","rate":"40,202.5000","description":"Chinese Yuan","rate_float":40202.5}}}