{"time":{"updated":"Aug 24, 2024 21:46:27 UTC","updatedISO":"2024-08-24T21:46:27+00:00","updateduk":"Aug 24, 2024 at 22:46 BST"},"disclaimer":"This data was produced from the CoinDesk Bitcoin Price Index (USD). Non-USD currency data converted using hourly conversion rate from openexchangerates.org","chartName":"Bitcoin","bpi":{"USD":{"code":"USD","symbol":"&#36;","rate":"63,915.3","description":"United States Dollar","rate_float":63915.2998},"GBP":{"code":"GBP","symbol":"&pound;","rate":"48,356.59","description":"British Pound Sterling","rate_float":48356.5901},"EUR":{"code":"EUR","symbol":"&euro;","rate":"57,102.951","description":"Euro","rate_float":57102.9514},"CNY":{"code":"CNY","symbol":"&yen;","rate":"455,275.072","description":"Chinese Yuan","rate_float":455275.0717}}}