{"time":{"updated":"Apr 28, 2024 20:38:17 UTC","updatedISO":"2024-04-28T20:38:17+00:00","updateduk":"Apr 28, 2024 at 21:38 BST"},"disclaimer":"This data was produced from the CoinDesk Bitcoin Price Index (USD). Non-USD currency data converted using hourly conversion rate from openexchangerates.org","chartName":"Bitcoin","bpi":{"USD":{"code":"USD","symbol":"&#36;","rate":"63,669.81","description":"United States Dollar","rate_float":63669.81},"GBP":{"code":"GBP","symbol":"&pound;","rate":"50,988.758","description":"British Pound Sterling","rate_float":50988.7576},"EUR":{"code":"EUR","symbol":"&euro;","rate":"59,529.553","description":"Euro","rate_float":59529.5533},"CNY":{"code":"CNY","symbol":"&yen;","rate":"461,325.976","description":"Chinese Yuan","rate_float":461325.9757}}}