{"time":{"updated":"Jun 12, 2024 11:51:26 UTC","updatedISO":"2024-06-12T11:51:26+00:00","updateduk":"Jun 12, 2024 at 12:51 BST"},"disclaimer":"This data was produced from the CoinDesk Bitcoin Price Index (USD). Non-USD currency data converted using hourly conversion rate from openexchangerates.org","chartName":"Bitcoin","bpi":{"USD":{"code":"USD","symbol":"&#36;","rate":"67,815.742","description":"United States Dollar","rate_float":67815.7421},"GBP":{"code":"GBP","symbol":"&pound;","rate":"53,142.993","description":"British Pound Sterling","rate_float":53142.9925},"EUR":{"code":"EUR","symbol":"&euro;","rate":"63,032.359","description":"Euro","rate_float":63032.3588},"CNY":{"code":"CNY","symbol":"&yen;","rate":"481,952.916","description":"Chinese Yuan","rate_float":481952.9163}}}