{"time":{"updated":"Jan 8, 2025 12:52:56 UTC","updatedISO":"2025-01-08T12:52:56+00:00","updateduk":"Jan 8, 2025 at 12:52 GMT"},"disclaimer":"This data was produced from the CoinDesk Bitcoin Price Index (USD). Non-USD currency data converted using hourly conversion rate from openexchangerates.org","chartName":"Bitcoin","bpi":{"USD":{"code":"USD","symbol":"&#36;","rate":"96,047.11","description":"United States Dollar","rate_float":96047.1099},"GBP":{"code":"GBP","symbol":"&pound;","rate":"76,604.774","description":"British Pound Sterling","rate_float":76604.7737},"EUR":{"code":"EUR","symbol":"&euro;","rate":"92,371.771","description":"Euro","rate_float":92371.7712},"CNY":{"code":"CNY","symbol":"&yen;","rate":"703,823.617","description":"Chinese Yuan","rate_float":703823.6169}}}