{"time":{"updated":"May 1, 2024 23:58:55 UTC","updatedISO":"2024-05-01T23:58:55+00:00","updateduk":"May 2, 2024 at 00:58 BST"},"disclaimer":"This data was produced from the CoinDesk Bitcoin Price Index (USD). Non-USD currency data converted using hourly conversion rate from openexchangerates.org","chartName":"Bitcoin","bpi":{"USD":{"code":"USD","symbol":"&#36;","rate":"58,329.853","description":"United States Dollar","rate_float":58329.853},"GBP":{"code":"GBP","symbol":"&pound;","rate":"46,532.29","description":"British Pound Sterling","rate_float":46532.2903},"EUR":{"code":"EUR","symbol":"&euro;","rate":"54,422.978","description":"Euro","rate_float":54422.9778},"CNY":{"code":"CNY","symbol":"&yen;","rate":"422,360.633","description":"Chinese Yuan","rate_float":422360.6328}}}