{"time":{"updated":"Mar 14, 2024 10:16:13 UTC","updatedISO":"2024-03-14T10:16:13+00:00","updateduk":"Mar 14, 2024 at 10:16 GMT"},"disclaimer":"This data was produced from the CoinDesk Bitcoin Price Index (USD). Non-USD currency data converted using hourly conversion rate from openexchangerates.org","chartName":"Bitcoin","bpi":{"USD":{"code":"USD","symbol":"&#36;","rate":"73,085.671","description":"United States Dollar","rate_float":73085.6705},"GBP":{"code":"GBP","symbol":"&pound;","rate":"57,027.433","description":"British Pound Sterling","rate_float":57027.4331},"EUR":{"code":"EUR","symbol":"&euro;","rate":"66,799.207","description":"Euro","rate_float":66799.2065},"CNY":{"code":"CNY","symbol":"&yen;","rate":"525,427.502","description":"Chinese Yuan","rate_float":525427.5021}}}