{"time":{"updated":"Feb 4, 2025 14:48:23 UTC","updatedISO":"2025-02-04T14:48:23+00:00","updateduk":"Feb 4, 2025 at 14:48 GMT"},"disclaimer":"This data was produced from the CoinDesk Bitcoin Price Index (USD). Non-USD currency data converted using hourly conversion rate from openexchangerates.org","chartName":"Bitcoin","bpi":{"USD":{"code":"USD","symbol":"&#36;","rate":"100,991.081","description":"United States Dollar","rate_float":100991.0807},"GBP":{"code":"GBP","symbol":"&pound;","rate":"81,104.624","description":"British Pound Sterling","rate_float":81104.624},"EUR":{"code":"EUR","symbol":"&euro;","rate":"96,555.25","description":"Euro","rate_float":96555.2495},"CNY":{"code":"CNY","symbol":"&yen;","rate":"733,871.886","description":"Chinese Yuan","rate_float":733871.8861}}}