{"time":{"updated":"Jul 27, 2024 13:29:04 UTC","updatedISO":"2024-07-27T13:29:04+00:00","updateduk":"Jul 27, 2024 at 14:29 BST"},"disclaimer":"This data was produced from the CoinDesk Bitcoin Price Index (USD). Non-USD currency data converted using hourly conversion rate from openexchangerates.org","chartName":"Bitcoin","bpi":{"USD":{"code":"USD","symbol":"&#36;","rate":"68,888.922","description":"United States Dollar","rate_float":68888.9218},"GBP":{"code":"GBP","symbol":"&pound;","rate":"53,535.097","description":"British Pound Sterling","rate_float":53535.0967},"EUR":{"code":"EUR","symbol":"&euro;","rate":"63,366.51","description":"Euro","rate_float":63366.5103},"CNY":{"code":"CNY","symbol":"&yen;","rate":"499,472.239","description":"Chinese Yuan","rate_float":499472.2387}}}