{"time":{"updated":"Aug 23, 2024 13:52:54 UTC","updatedISO":"2024-08-23T13:52:54+00:00","updateduk":"Aug 23, 2024 at 14:52 BST"},"disclaimer":"This data was produced from the CoinDesk Bitcoin Price Index (USD). Non-USD currency data converted using hourly conversion rate from openexchangerates.org","chartName":"Bitcoin","bpi":{"USD":{"code":"USD","symbol":"&#36;","rate":"61,004.194","description":"United States Dollar","rate_float":61004.1935},"GBP":{"code":"GBP","symbol":"&pound;","rate":"46,498.738","description":"British Pound Sterling","rate_float":46498.7384},"EUR":{"code":"EUR","symbol":"&euro;","rate":"54,888.096","description":"Euro","rate_float":54888.096},"CNY":{"code":"CNY","symbol":"&yen;","rate":"435,393.029","description":"Chinese Yuan","rate_float":435393.0292}}}