{"time":{"updated":"Jan 10, 2022 17:31:00 UTC","updatedISO":"2022-01-10T17:31:00+00:00","updateduk":"Jan 10, 2022 at 17:31 GMT"},"disclaimer":"This data was produced from the CoinDesk Bitcoin Price Index (USD). Non-USD currency data converted using hourly conversion rate from openexchangerates.org","chartName":"Bitcoin","bpi":{"USD":{"code":"USD","symbol":"&#36;","rate":"40,749.6123","description":"United States Dollar","rate_float":40749.6123},"GBP":{"code":"GBP","symbol":"&pound;","rate":"30,038.9434","description":"British Pound Sterling","rate_float":30038.9434},"EUR":{"code":"EUR","symbol":"&euro;","rate":"35,973.8392","description":"Euro","rate_float":35973.8392},"CNY":{"code":"CNY","symbol":"&yen;","rate":"40,202.5000","description":"Chinese Yuan","rate_float":40202.5}}}