{"time":{"updated":"Aug 21, 2024 19:45:54 UTC","updatedISO":"2024-08-21T19:45:54+00:00","updateduk":"Aug 21, 2024 at 20:45 BST"},"disclaimer":"This data was produced from the CoinDesk Bitcoin Price Index (USD). Non-USD currency data converted using hourly conversion rate from openexchangerates.org","chartName":"Bitcoin","bpi":{"USD":{"code":"USD","symbol":"&#36;","rate":"61,258.457","description":"United States Dollar","rate_float":61258.4565},"GBP":{"code":"GBP","symbol":"&pound;","rate":"46,740.08","description":"British Pound Sterling","rate_float":46740.0798},"EUR":{"code":"EUR","symbol":"&euro;","rate":"54,882.493","description":"Euro","rate_float":54882.4925},"CNY":{"code":"CNY","symbol":"&yen;","rate":"436,999.451","description":"Chinese Yuan","rate_float":436999.4509}}}