{"time":{"updated":"Jan 19, 2025 03:11:28 UTC","updatedISO":"2025-01-19T03:11:28+00:00","updateduk":"Jan 19, 2025 at 03:11 GMT"},"disclaimer":"This data was produced from the CoinDesk Bitcoin Price Index (USD). Non-USD currency data converted using hourly conversion rate from openexchangerates.org","chartName":"Bitcoin","bpi":{"USD":{"code":"USD","symbol":"&#36;","rate":"105,274.707","description":"United States Dollar","rate_float":105274.7071},"GBP":{"code":"GBP","symbol":"&pound;","rate":"83,964.475","description":"British Pound Sterling","rate_float":83964.4745},"EUR":{"code":"EUR","symbol":"&euro;","rate":"101,246.265","description":"Euro","rate_float":101246.2651},"CNY":{"code":"CNY","symbol":"&yen;","rate":"771,442.526","description":"Chinese Yuan","rate_float":771442.5258}}}