{"time":{"updated":"May 24, 2024 10:00:20 UTC","updatedISO":"2024-05-24T10:00:20+00:00","updateduk":"May 24, 2024 at 11:00 BST"},"disclaimer":"This data was produced from the CoinDesk Bitcoin Price Index (USD). Non-USD currency data converted using hourly conversion rate from openexchangerates.org","chartName":"Bitcoin","bpi":{"USD":{"code":"USD","symbol":"&#36;","rate":"67,401.248","description":"United States Dollar","rate_float":67401.2481},"GBP":{"code":"GBP","symbol":"&pound;","rate":"53,050.04","description":"British Pound Sterling","rate_float":53050.0396},"EUR":{"code":"EUR","symbol":"&euro;","rate":"62,263.251","description":"Euro","rate_float":62263.251},"CNY":{"code":"CNY","symbol":"&yen;","rate":"479,168.953","description":"Chinese Yuan","rate_float":479168.953}}}