{"time":{"updated":"Oct 8, 2024 11:12:33 UTC","updatedISO":"2024-10-08T11:12:33+00:00","updateduk":"Oct 8, 2024 at 12:12 BST"},"disclaimer":"This data was produced from the CoinDesk Bitcoin Price Index (USD). Non-USD currency data converted using hourly conversion rate from openexchangerates.org","chartName":"Bitcoin","bpi":{"USD":{"code":"USD","symbol":"&#36;","rate":"62,487.57","description":"United States Dollar","rate_float":62487.57},"GBP":{"code":"GBP","symbol":"&pound;","rate":"47,696.95","description":"British Pound Sterling","rate_float":47696.9496},"EUR":{"code":"EUR","symbol":"&euro;","rate":"56,884.185","description":"Euro","rate_float":56884.1846},"CNY":{"code":"CNY","symbol":"&yen;","rate":"440,699.836","description":"Chinese Yuan","rate_float":440699.8361}}}