{"time":{"updated":"Jan 7, 2025 18:55:26 UTC","updatedISO":"2025-01-07T18:55:26+00:00","updateduk":"Jan 7, 2025 at 18:55 GMT"},"disclaimer":"This data was produced from the CoinDesk Bitcoin Price Index (USD). Non-USD currency data converted using hourly conversion rate from openexchangerates.org","chartName":"Bitcoin","bpi":{"USD":{"code":"USD","symbol":"&#36;","rate":"97,261.368","description":"United States Dollar","rate_float":97261.3679},"GBP":{"code":"GBP","symbol":"&pound;","rate":"77,573.236","description":"British Pound Sterling","rate_float":77573.2355},"EUR":{"code":"EUR","symbol":"&euro;","rate":"93,539.564","description":"Euro","rate_float":93539.5644},"CNY":{"code":"CNY","symbol":"&yen;","rate":"712,721.578","description":"Chinese Yuan","rate_float":712721.5782}}}