{"time":{"updated":"Jan 20, 2025 22:04:14 UTC","updatedISO":"2025-01-20T22:04:14+00:00","updateduk":"Jan 20, 2025 at 22:04 GMT"},"disclaimer":"This data was produced from the CoinDesk Bitcoin Price Index (USD). Non-USD currency data converted using hourly conversion rate from openexchangerates.org","chartName":"Bitcoin","bpi":{"USD":{"code":"USD","symbol":"&#36;","rate":"101,774.882","description":"United States Dollar","rate_float":101774.8822},"GBP":{"code":"GBP","symbol":"&pound;","rate":"81,173.102","description":"British Pound Sterling","rate_float":81173.1017},"EUR":{"code":"EUR","symbol":"&euro;","rate":"97,880.365","description":"Euro","rate_float":97880.3646},"CNY":{"code":"CNY","symbol":"&yen;","rate":"745,796.159","description":"Chinese Yuan","rate_float":745796.1594}}}