{"time":{"updated":"Oct 28, 2024 06:58:53 UTC","updatedISO":"2024-10-28T06:58:53+00:00","updateduk":"Oct 28, 2024 at 06:58 GMT"},"disclaimer":"This data was produced from the CoinDesk Bitcoin Price Index (USD). Non-USD currency data converted using hourly conversion rate from openexchangerates.org","chartName":"Bitcoin","bpi":{"USD":{"code":"USD","symbol":"&#36;","rate":"67,831.943","description":"United States Dollar","rate_float":67831.943},"GBP":{"code":"GBP","symbol":"&pound;","rate":"52,386.745","description":"British Pound Sterling","rate_float":52386.7453},"EUR":{"code":"EUR","symbol":"&euro;","rate":"62,879.804","description":"Euro","rate_float":62879.8042},"CNY":{"code":"CNY","symbol":"&yen;","rate":"483,804.551","description":"Chinese Yuan","rate_float":483804.5505}}}