{"time":{"updated":"Apr 30, 2024 18:29:55 UTC","updatedISO":"2024-04-30T18:29:55+00:00","updateduk":"Apr 30, 2024 at 19:29 BST"},"disclaimer":"This data was produced from the CoinDesk Bitcoin Price Index (USD). Non-USD currency data converted using hourly conversion rate from openexchangerates.org","chartName":"Bitcoin","bpi":{"USD":{"code":"USD","symbol":"&#36;","rate":"60,331.815","description":"United States Dollar","rate_float":60331.8147},"GBP":{"code":"GBP","symbol":"&pound;","rate":"48,231.485","description":"British Pound Sterling","rate_float":48231.485},"EUR":{"code":"EUR","symbol":"&euro;","rate":"56,489.342","description":"Euro","rate_float":56489.3418},"CNY":{"code":"CNY","symbol":"&yen;","rate":"436,862.67","description":"Chinese Yuan","rate_float":436862.6704}}}