{"time":{"updated":"Sep 25, 2024 22:41:48 UTC","updatedISO":"2024-09-25T22:41:48+00:00","updateduk":"Sep 25, 2024 at 23:41 BST"},"disclaimer":"This data was produced from the CoinDesk Bitcoin Price Index (USD). Non-USD currency data converted using hourly conversion rate from openexchangerates.org","chartName":"Bitcoin","bpi":{"USD":{"code":"USD","symbol":"&#36;","rate":"63,220.543","description":"United States Dollar","rate_float":63220.5429},"GBP":{"code":"GBP","symbol":"&pound;","rate":"47,454.477","description":"British Pound Sterling","rate_float":47454.4774},"EUR":{"code":"EUR","symbol":"&euro;","rate":"56,783.87","description":"Euro","rate_float":56783.8697},"CNY":{"code":"CNY","symbol":"&yen;","rate":"444,598.468","description":"Chinese Yuan","rate_float":444598.4677}}}