{"time":{"updated":"Nov 7, 2024 14:23:34 UTC","updatedISO":"2024-11-07T14:23:34+00:00","updateduk":"Nov 7, 2024 at 14:23 GMT"},"disclaimer":"This data was produced from the CoinDesk Bitcoin Price Index (USD). Non-USD currency data converted using hourly conversion rate from openexchangerates.org","chartName":"Bitcoin","bpi":{"USD":{"code":"USD","symbol":"&#36;","rate":"74,871.335","description":"United States Dollar","rate_float":74871.3351},"GBP":{"code":"GBP","symbol":"&pound;","rate":"57,714.718","description":"British Pound Sterling","rate_float":57714.7184},"EUR":{"code":"EUR","symbol":"&euro;","rate":"69,375.629","description":"Euro","rate_float":69375.6293},"CNY":{"code":"CNY","symbol":"&yen;","rate":"535,150.355","description":"Chinese Yuan","rate_float":535150.3546}}}