{"time":{"updated":"Mar 30, 2024 03:17:58 UTC","updatedISO":"2024-03-30T03:17:58+00:00","updateduk":"Mar 30, 2024 at 03:17 GMT"},"disclaimer":"This data was produced from the CoinDesk Bitcoin Price Index (USD). Non-USD currency data converted using hourly conversion rate from openexchangerates.org","chartName":"Bitcoin","bpi":{"USD":{"code":"USD","symbol":"&#36;","rate":"70,094.229","description":"United States Dollar","rate_float":70094.2289},"GBP":{"code":"GBP","symbol":"&pound;","rate":"55,515.751","description":"British Pound Sterling","rate_float":55515.7508},"EUR":{"code":"EUR","symbol":"&euro;","rate":"64,901.438","description":"Euro","rate_float":64901.4381},"CNY":{"code":"CNY","symbol":"&yen;","rate":"506,164.446","description":"Chinese Yuan","rate_float":506164.4456}}}