{"time":{"updated":"Feb 5, 2025 00:23:31 UTC","updatedISO":"2025-02-05T00:23:31+00:00","updateduk":"Feb 5, 2025 at 00:23 GMT"},"disclaimer":"This data was produced from the CoinDesk Bitcoin Price Index (USD). Non-USD currency data converted using hourly conversion rate from openexchangerates.org","chartName":"Bitcoin","bpi":{"USD":{"code":"USD","symbol":"&#36;","rate":"98,888.6","description":"United States Dollar","rate_float":98888.5999},"GBP":{"code":"GBP","symbol":"&pound;","rate":"79,416.149","description":"British Pound Sterling","rate_float":79416.149},"EUR":{"code":"EUR","symbol":"&euro;","rate":"94,545.116","description":"Euro","rate_float":94545.1159},"CNY":{"code":"CNY","symbol":"&yen;","rate":"718,593.789","description":"Chinese Yuan","rate_float":718593.7888}}}