{"time":{"updated":"May 30, 2024 13:53:05 UTC","updatedISO":"2024-05-30T13:53:05+00:00","updateduk":"May 30, 2024 at 14:53 BST"},"disclaimer":"This data was produced from the CoinDesk Bitcoin Price Index (USD). Non-USD currency data converted using hourly conversion rate from openexchangerates.org","chartName":"Bitcoin","bpi":{"USD":{"code":"USD","symbol":"&#36;","rate":"68,573.002","description":"United States Dollar","rate_float":68573.0023},"GBP":{"code":"GBP","symbol":"&pound;","rate":"53,891.728","description":"British Pound Sterling","rate_float":53891.7282},"EUR":{"code":"EUR","symbol":"&euro;","rate":"63,323.122","description":"Euro","rate_float":63323.1218},"CNY":{"code":"CNY","symbol":"&yen;","rate":"494,013.623","description":"Chinese Yuan","rate_float":494013.6229}}}