{"time":{"updated":"Mar 4, 2024 03:31:53 UTC","updatedISO":"2024-03-04T03:31:53+00:00","updateduk":"Mar 4, 2024 at 03:31 GMT"},"disclaimer":"This data was produced from the CoinDesk Bitcoin Price Index (USD). Non-USD currency data converted using hourly conversion rate from openexchangerates.org","chartName":"Bitcoin","bpi":{"USD":{"code":"USD","symbol":"&#36;","rate":"63,718.011","description":"United States Dollar","rate_float":63718.0106},"GBP":{"code":"GBP","symbol":"&pound;","rate":"50,308.364","description":"British Pound Sterling","rate_float":50308.3641},"EUR":{"code":"EUR","symbol":"&euro;","rate":"58,756.034","description":"Euro","rate_float":58756.0343},"CNY":{"code":"CNY","symbol":"&yen;","rate":"458,680.471","description":"Chinese Yuan","rate_float":458680.4712}}}