{"time":{"updated":"Nov 26, 2024 13:48:04 UTC","updatedISO":"2024-11-26T13:48:04+00:00","updateduk":"Nov 26, 2024 at 13:48 GMT"},"disclaimer":"This data was produced from the CoinDesk Bitcoin Price Index (USD). Non-USD currency data converted using hourly conversion rate from openexchangerates.org","chartName":"Bitcoin","bpi":{"USD":{"code":"USD","symbol":"&#36;","rate":"92,504.578","description":"United States Dollar","rate_float":92504.5777},"GBP":{"code":"GBP","symbol":"&pound;","rate":"73,375.279","description":"British Pound Sterling","rate_float":73375.2786},"EUR":{"code":"EUR","symbol":"&euro;","rate":"87,890.727","description":"Euro","rate_float":87890.7269},"CNY":{"code":"CNY","symbol":"&yen;","rate":"670,265.044","description":"Chinese Yuan","rate_float":670265.0438}}}