{"time":{"updated":"Nov 14, 2024 02:36:46 UTC","updatedISO":"2024-11-14T02:36:46+00:00","updateduk":"Nov 14, 2024 at 02:36 GMT"},"disclaimer":"This data was produced from the CoinDesk Bitcoin Price Index (USD). Non-USD currency data converted using hourly conversion rate from openexchangerates.org","chartName":"Bitcoin","bpi":{"USD":{"code":"USD","symbol":"&#36;","rate":"89,608.391","description":"United States Dollar","rate_float":89608.3911},"GBP":{"code":"GBP","symbol":"&pound;","rate":"70,589.279","description":"British Pound Sterling","rate_float":70589.2789},"EUR":{"code":"EUR","symbol":"&euro;","rate":"84,887.194","description":"Euro","rate_float":84887.1938},"CNY":{"code":"CNY","symbol":"&yen;","rate":"648,943.969","description":"Chinese Yuan","rate_float":648943.9686}}}