{"time":{"updated":"Apr 1, 2024 18:19:04 UTC","updatedISO":"2024-04-01T18:19:04+00:00","updateduk":"Apr 1, 2024 at 19:19 BST"},"disclaimer":"This data was produced from the CoinDesk Bitcoin Price Index (USD). Non-USD currency data converted using hourly conversion rate from openexchangerates.org","chartName":"Bitcoin","bpi":{"USD":{"code":"USD","symbol":"&#36;","rate":"68,636.388","description":"United States Dollar","rate_float":68636.3875},"GBP":{"code":"GBP","symbol":"&pound;","rate":"54,710.339","description":"British Pound Sterling","rate_float":54710.339},"EUR":{"code":"EUR","symbol":"&euro;","rate":"63,928.48","description":"Euro","rate_float":63928.4804},"CNY":{"code":"CNY","symbol":"&yen;","rate":"496,295.991","description":"Chinese Yuan","rate_float":496295.9905}}}