{"time":{"updated":"Aug 22, 2024 21:36:22 UTC","updatedISO":"2024-08-22T21:36:22+00:00","updateduk":"Aug 22, 2024 at 22:36 BST"},"disclaimer":"This data was produced from the CoinDesk Bitcoin Price Index (USD). Non-USD currency data converted using hourly conversion rate from openexchangerates.org","chartName":"Bitcoin","bpi":{"USD":{"code":"USD","symbol":"&#36;","rate":"60,648.521","description":"United States Dollar","rate_float":60648.5212},"GBP":{"code":"GBP","symbol":"&pound;","rate":"46,325.403","description":"British Pound Sterling","rate_float":46325.4026},"EUR":{"code":"EUR","symbol":"&euro;","rate":"54,578.696","description":"Euro","rate_float":54578.6959},"CNY":{"code":"CNY","symbol":"&yen;","rate":"433,339.142","description":"Chinese Yuan","rate_float":433339.1424}}}