{"time":{"updated":"Mar 25, 2024 04:51:28 UTC","updatedISO":"2024-03-25T04:51:28+00:00","updateduk":"Mar 25, 2024 at 04:51 GMT"},"disclaimer":"This data was produced from the CoinDesk Bitcoin Price Index (USD). Non-USD currency data converted using hourly conversion rate from openexchangerates.org","chartName":"Bitcoin","bpi":{"USD":{"code":"USD","symbol":"&#36;","rate":"67,494.275","description":"United States Dollar","rate_float":67494.2745},"GBP":{"code":"GBP","symbol":"&pound;","rate":"53,540.508","description":"British Pound Sterling","rate_float":53540.5082},"EUR":{"code":"EUR","symbol":"&euro;","rate":"62,415.803","description":"Euro","rate_float":62415.8028},"CNY":{"code":"CNY","symbol":"&yen;","rate":"487,396.404","description":"Chinese Yuan","rate_float":487396.4043}}}