{"time":{"updated":"Aug 15, 2024 20:50:27 UTC","updatedISO":"2024-08-15T20:50:27+00:00","updateduk":"Aug 15, 2024 at 21:50 BST"},"disclaimer":"This data was produced from the CoinDesk Bitcoin Price Index (USD). Non-USD currency data converted using hourly conversion rate from openexchangerates.org","chartName":"Bitcoin","bpi":{"USD":{"code":"USD","symbol":"&#36;","rate":"56,843.809","description":"United States Dollar","rate_float":56843.8093},"GBP":{"code":"GBP","symbol":"&pound;","rate":"44,219.822","description":"British Pound Sterling","rate_float":44219.8224},"EUR":{"code":"EUR","symbol":"&euro;","rate":"51,798.125","description":"Euro","rate_float":51798.1254},"CNY":{"code":"CNY","symbol":"&yen;","rate":"407,359.79","description":"Chinese Yuan","rate_float":407359.7902}}}