{"time":{"updated":"Jan 6, 2024 07:42:30 UTC","updatedISO":"2024-01-06T07:42:30+00:00","updateduk":"Jan 6, 2024 at 07:42 GMT"},"disclaimer":"This data was produced from the CoinDesk Bitcoin Price Index (USD). Non-USD currency data converted using hourly conversion rate from openexchangerates.org","chartName":"Bitcoin","bpi":{"USD":{"code":"USD","symbol":"&#36;","rate":"43,762.926","description":"United States Dollar","rate_float":43762.9255},"GBP":{"code":"GBP","symbol":"&pound;","rate":"34,391.314","description":"British Pound Sterling","rate_float":34391.3138},"EUR":{"code":"EUR","symbol":"&euro;","rate":"39,948.987","description":"Euro","rate_float":39948.9866},"CNY":{"code":"CNY","symbol":"&yen;","rate":"310,751.782","description":"Chinese Yuan","rate_float":310751.7815}}}