{"time":{"updated":"Jul 18, 2022 17:42:00 UTC","updatedISO":"2022-07-18T17:42:00+00:00","updateduk":"Jul 18, 2022 at 18:42 BST"},"disclaimer":"This data was produced from the CoinDesk Bitcoin Price Index (USD). Non-USD currency data converted using hourly conversion rate from openexchangerates.org","chartName":"Bitcoin","bpi":{"USD":{"code":"USD","symbol":"&#36;","rate":"22,024.0686","description":"United States Dollar","rate_float":22024.0686},"GBP":{"code":"GBP","symbol":"&pound;","rate":"18,403.1355","description":"British Pound Sterling","rate_float":18403.1355},"EUR":{"code":"EUR","symbol":"&euro;","rate":"21,454.6583","description":"Euro","rate_float":21454.6583},"CNY":{"code":"CNY","symbol":"&yen;","rate":"40,202.5000","description":"Chinese Yuan","rate_float":40202.5}}}