{"time":{"updated":"Jul 15, 2024 03:49:03 UTC","updatedISO":"2024-07-15T03:49:03+00:00","updateduk":"Jul 15, 2024 at 04:49 BST"},"disclaimer":"This data was produced from the CoinDesk Bitcoin Price Index (USD). Non-USD currency data converted using hourly conversion rate from openexchangerates.org","chartName":"Bitcoin","bpi":{"USD":{"code":"USD","symbol":"&#36;","rate":"62,804.318","description":"United States Dollar","rate_float":62804.3179},"GBP":{"code":"GBP","symbol":"&pound;","rate":"48,422.569","description":"British Pound Sterling","rate_float":48422.5688},"EUR":{"code":"EUR","symbol":"&euro;","rate":"57,654.364","description":"Euro","rate_float":57654.3639},"CNY":{"code":"CNY","symbol":"&yen;","rate":"455,356.427","description":"Chinese Yuan","rate_float":455356.4267}}}