{"time":{"updated":"Jun 23, 2022 07:05:00 UTC","updatedISO":"2022-06-23T07:05:00+00:00","updateduk":"Jun 23, 2022 at 08:05 BST"},"disclaimer":"This data was produced from the CoinDesk Bitcoin Price Index (USD). Non-USD currency data converted using hourly conversion rate from openexchangerates.org","chartName":"Bitcoin","bpi":{"USD":{"code":"USD","symbol":"&#36;","rate":"20,559.0007","description":"United States Dollar","rate_float":20559.0007},"GBP":{"code":"GBP","symbol":"&pound;","rate":"16,692.2432","description":"British Pound Sterling","rate_float":16692.2432},"EUR":{"code":"EUR","symbol":"&euro;","rate":"19,542.7692","description":"Euro","rate_float":19542.7692},"CNY":{"code":"CNY","symbol":"&yen;","rate":"40,202.5000","description":"Chinese Yuan","rate_float":40202.5}}}