{"time":{"updated":"Aug 24, 2024 03:44:51 UTC","updatedISO":"2024-08-24T03:44:51+00:00","updateduk":"Aug 24, 2024 at 04:44 BST"},"disclaimer":"This data was produced from the CoinDesk Bitcoin Price Index (USD). Non-USD currency data converted using hourly conversion rate from openexchangerates.org","chartName":"Bitcoin","bpi":{"USD":{"code":"USD","symbol":"&#36;","rate":"63,888.362","description":"United States Dollar","rate_float":63888.3615},"GBP":{"code":"GBP","symbol":"&pound;","rate":"48,352.629","description":"British Pound Sterling","rate_float":48352.6287},"EUR":{"code":"EUR","symbol":"&euro;","rate":"57,029.946","description":"Euro","rate_float":57029.9459},"CNY":{"code":"CNY","symbol":"&yen;","rate":"455,083.188","description":"Chinese Yuan","rate_float":455083.188}}}