{"time":{"updated":"Oct 10, 2024 03:38:02 UTC","updatedISO":"2024-10-10T03:38:02+00:00","updateduk":"Oct 10, 2024 at 04:38 BST"},"disclaimer":"This data was produced from the CoinDesk Bitcoin Price Index (USD). Non-USD currency data converted using hourly conversion rate from openexchangerates.org","chartName":"Bitcoin","bpi":{"USD":{"code":"USD","symbol":"&#36;","rate":"60,897.735","description":"United States Dollar","rate_float":60897.7354},"GBP":{"code":"GBP","symbol":"&pound;","rate":"46,586.402","description":"British Pound Sterling","rate_float":46586.4022},"EUR":{"code":"EUR","symbol":"&euro;","rate":"55,655.11","description":"Euro","rate_float":55655.1103},"CNY":{"code":"CNY","symbol":"&yen;","rate":"430,339.937","description":"Chinese Yuan","rate_float":430339.9372}}}