{"time":{"updated":"Jun 8, 2024 03:08:30 UTC","updatedISO":"2024-06-08T03:08:30+00:00","updateduk":"Jun 8, 2024 at 04:08 BST"},"disclaimer":"This data was produced from the CoinDesk Bitcoin Price Index (USD). Non-USD currency data converted using hourly conversion rate from openexchangerates.org","chartName":"Bitcoin","bpi":{"USD":{"code":"USD","symbol":"&#36;","rate":"69,557.239","description":"United States Dollar","rate_float":69557.2394},"GBP":{"code":"GBP","symbol":"&pound;","rate":"54,648.967","description":"British Pound Sterling","rate_float":54648.9667},"EUR":{"code":"EUR","symbol":"&euro;","rate":"64,361.314","description":"Euro","rate_float":64361.3136},"CNY":{"code":"CNY","symbol":"&yen;","rate":"504,053.491","description":"Chinese Yuan","rate_float":504053.4907}}}