{"time":{"updated":"Aug 1, 2024 08:09:07 UTC","updatedISO":"2024-08-01T08:09:07+00:00","updateduk":"Aug 1, 2024 at 09:09 BST"},"disclaimer":"This data was produced from the CoinDesk Bitcoin Price Index (USD). Non-USD currency data converted using hourly conversion rate from openexchangerates.org","chartName":"Bitcoin","bpi":{"USD":{"code":"USD","symbol":"&#36;","rate":"64,542.04","description":"United States Dollar","rate_float":64542.0399},"GBP":{"code":"GBP","symbol":"&pound;","rate":"50,398.104","description":"British Pound Sterling","rate_float":50398.1037},"EUR":{"code":"EUR","symbol":"&euro;","rate":"59,671.633","description":"Euro","rate_float":59671.633},"CNY":{"code":"CNY","symbol":"&yen;","rate":"467,077.835","description":"Chinese Yuan","rate_float":467077.8345}}}