{"time":{"updated":"Dec 28, 2024 03:38:37 UTC","updatedISO":"2024-12-28T03:38:37+00:00","updateduk":"Dec 28, 2024 at 03:38 GMT"},"disclaimer":"This data was produced from the CoinDesk Bitcoin Price Index (USD). Non-USD currency data converted using hourly conversion rate from openexchangerates.org","chartName":"Bitcoin","bpi":{"USD":{"code":"USD","symbol":"&#36;","rate":"94,486.498","description":"United States Dollar","rate_float":94486.4984},"GBP":{"code":"GBP","symbol":"&pound;","rate":"75,351.093","description":"British Pound Sterling","rate_float":75351.0927},"EUR":{"code":"EUR","symbol":"&euro;","rate":"90,647.606","description":"Euro","rate_float":90647.6064},"CNY":{"code":"CNY","symbol":"&yen;","rate":"689,619.157","description":"Chinese Yuan","rate_float":689619.1571}}}