{"time":{"updated":"Dec 9, 2024 22:34:36 UTC","updatedISO":"2024-12-09T22:34:36+00:00","updateduk":"Dec 9, 2024 at 22:34 GMT"},"disclaimer":"This data was produced from the CoinDesk Bitcoin Price Index (USD). Non-USD currency data converted using hourly conversion rate from openexchangerates.org","chartName":"Bitcoin","bpi":{"USD":{"code":"USD","symbol":"&#36;","rate":"97,329.085","description":"United States Dollar","rate_float":97329.0848},"GBP":{"code":"GBP","symbol":"&pound;","rate":"76,334.131","description":"British Pound Sterling","rate_float":76334.1306},"EUR":{"code":"EUR","symbol":"&euro;","rate":"92,221.157","description":"Euro","rate_float":92221.1571},"CNY":{"code":"CNY","symbol":"&yen;","rate":"706,700.645","description":"Chinese Yuan","rate_float":706700.6449}}}