{"time":{"updated":"Feb 25, 2023 13:05:00 UTC","updatedISO":"2023-02-25T13:05:00+00:00","updateduk":"Feb 25, 2023 at 13:05 GMT"},"disclaimer":"This data was produced from the CoinDesk Bitcoin Price Index (USD). Non-USD currency data converted using hourly conversion rate from openexchangerates.org","chartName":"Bitcoin","bpi":{"USD":{"code":"USD","symbol":"&#36;","rate":"23,036.1850","description":"United States Dollar","rate_float":23036.185},"GBP":{"code":"GBP","symbol":"&pound;","rate":"19,248.8519","description":"British Pound Sterling","rate_float":19248.8519},"EUR":{"code":"EUR","symbol":"&euro;","rate":"22,440.6075","description":"Euro","rate_float":22440.6075},"CNY":{"code":"CNY","symbol":"&yen;","rate":"40,202.5000","description":"Chinese Yuan","rate_float":40202.5}}}