{"time":{"updated":"Apr 9, 2024 00:37:23 UTC","updatedISO":"2024-04-09T00:37:23+00:00","updateduk":"Apr 9, 2024 at 01:37 BST"},"disclaimer":"This data was produced from the CoinDesk Bitcoin Price Index (USD). Non-USD currency data converted using hourly conversion rate from openexchangerates.org","chartName":"Bitcoin","bpi":{"USD":{"code":"USD","symbol":"&#36;","rate":"71,565.361","description":"United States Dollar","rate_float":71565.3605},"GBP":{"code":"GBP","symbol":"&pound;","rate":"56,539.855","description":"British Pound Sterling","rate_float":56539.8552},"EUR":{"code":"EUR","symbol":"&euro;","rate":"65,887.794","description":"Euro","rate_float":65887.7942},"CNY":{"code":"CNY","symbol":"&yen;","rate":"517,467.652","description":"Chinese Yuan","rate_float":517467.6522}}}