{"time":{"updated":"Aug 31, 2024 09:11:31 UTC","updatedISO":"2024-08-31T09:11:31+00:00","updateduk":"Aug 31, 2024 at 10:11 BST"},"disclaimer":"This data was produced from the CoinDesk Bitcoin Price Index (USD). Non-USD currency data converted using hourly conversion rate from openexchangerates.org","chartName":"Bitcoin","bpi":{"USD":{"code":"USD","symbol":"&#36;","rate":"58,969.997","description":"United States Dollar","rate_float":58969.9973},"GBP":{"code":"GBP","symbol":"&pound;","rate":"44,912.435","description":"British Pound Sterling","rate_float":44912.4345},"EUR":{"code":"EUR","symbol":"&euro;","rate":"53,312.888","description":"Euro","rate_float":53312.8875},"CNY":{"code":"CNY","symbol":"&yen;","rate":"418,280.088","description":"Chinese Yuan","rate_float":418280.088}}}