{"time":{"updated":"Sep 2, 2022 14:19:00 UTC","updatedISO":"2022-09-02T14:19:00+00:00","updateduk":"Sep 2, 2022 at 15:19 BST"},"disclaimer":"This data was produced from the CoinDesk Bitcoin Price Index (USD). Non-USD currency data converted using hourly conversion rate from openexchangerates.org","chartName":"Bitcoin","bpi":{"USD":{"code":"USD","symbol":"&#36;","rate":"20,315.2761","description":"United States Dollar","rate_float":20315.2761},"GBP":{"code":"GBP","symbol":"&pound;","rate":"16,975.2822","description":"British Pound Sterling","rate_float":16975.2822},"EUR":{"code":"EUR","symbol":"&euro;","rate":"19,790.0449","description":"Euro","rate_float":19790.0449},"CNY":{"code":"CNY","symbol":"&yen;","rate":"40,202.5000","description":"Chinese Yuan","rate_float":40202.5}}}