{"time":{"updated":"Jun 23, 2024 08:40:20 UTC","updatedISO":"2024-06-23T08:40:20+00:00","updateduk":"Jun 23, 2024 at 09:40 BST"},"disclaimer":"This data was produced from the CoinDesk Bitcoin Price Index (USD). Non-USD currency data converted using hourly conversion rate from openexchangerates.org","chartName":"Bitcoin","bpi":{"USD":{"code":"USD","symbol":"&#36;","rate":"64,342.095","description":"United States Dollar","rate_float":64342.0951},"GBP":{"code":"GBP","symbol":"&pound;","rate":"50,849.236","description":"British Pound Sterling","rate_float":50849.236},"EUR":{"code":"EUR","symbol":"&euro;","rate":"60,174.979","description":"Euro","rate_float":60174.9793},"CNY":{"code":"CNY","symbol":"&yen;","rate":"467,207.255","description":"Chinese Yuan","rate_float":467207.255}}}