{"time":{"updated":"Mar 6, 2024 15:45:41 UTC","updatedISO":"2024-03-06T15:45:41+00:00","updateduk":"Mar 6, 2024 at 15:45 GMT"},"disclaimer":"This data was produced from the CoinDesk Bitcoin Price Index (USD). Non-USD currency data converted using hourly conversion rate from openexchangerates.org","chartName":"Bitcoin","bpi":{"USD":{"code":"USD","symbol":"&#36;","rate":"66,604.335","description":"United States Dollar","rate_float":66604.335},"GBP":{"code":"GBP","symbol":"&pound;","rate":"52,340.75","description":"British Pound Sterling","rate_float":52340.7502},"EUR":{"code":"EUR","symbol":"&euro;","rate":"61,179.812","description":"Euro","rate_float":61179.8115},"CNY":{"code":"CNY","symbol":"&yen;","rate":"479,451.305","description":"Chinese Yuan","rate_float":479451.3054}}}