{"time":{"updated":"Dec 18, 2024 06:57:51 UTC","updatedISO":"2024-12-18T06:57:51+00:00","updateduk":"Dec 18, 2024 at 06:57 GMT"},"disclaimer":"This data was produced from the CoinDesk Bitcoin Price Index (USD). Non-USD currency data converted using hourly conversion rate from openexchangerates.org","chartName":"Bitcoin","bpi":{"USD":{"code":"USD","symbol":"&#36;","rate":"104,077.839","description":"United States Dollar","rate_float":104077.8392},"GBP":{"code":"GBP","symbol":"&pound;","rate":"81,438.099","description":"British Pound Sterling","rate_float":81438.099},"EUR":{"code":"EUR","symbol":"&euro;","rate":"98,827.112","description":"Euro","rate_float":98827.1122},"CNY":{"code":"CNY","symbol":"&yen;","rate":"754,533.111","description":"Chinese Yuan","rate_float":754533.1106}}}