{"time":{"updated":"Jul 21, 2024 23:59:16 UTC","updatedISO":"2024-07-21T23:59:16+00:00","updateduk":"Jul 22, 2024 at 00:59 BST"},"disclaimer":"This data was produced from the CoinDesk Bitcoin Price Index (USD). Non-USD currency data converted using hourly conversion rate from openexchangerates.org","chartName":"Bitcoin","bpi":{"USD":{"code":"USD","symbol":"&#36;","rate":"68,024.445","description":"United States Dollar","rate_float":68024.4451},"GBP":{"code":"GBP","symbol":"&pound;","rate":"52,594.052","description":"British Pound Sterling","rate_float":52594.0521},"EUR":{"code":"EUR","symbol":"&euro;","rate":"62,408.143","description":"Euro","rate_float":62408.1428},"CNY":{"code":"CNY","symbol":"&yen;","rate":"494,537.716","description":"Chinese Yuan","rate_float":494537.7158}}}