{"time":{"updated":"Apr 9, 2022 14:01:00 UTC","updatedISO":"2022-04-09T14:01:00+00:00","updateduk":"Apr 9, 2022 at 15:01 BST"},"disclaimer":"This data was produced from the CoinDesk Bitcoin Price Index (USD). Non-USD currency data converted using hourly conversion rate from openexchangerates.org","chartName":"Bitcoin","bpi":{"USD":{"code":"USD","symbol":"&#36;","rate":"42,487.4063","description":"United States Dollar","rate_float":42487.4063},"GBP":{"code":"GBP","symbol":"&pound;","rate":"32,593.8739","description":"British Pound Sterling","rate_float":32593.8739},"EUR":{"code":"EUR","symbol":"&euro;","rate":"39,063.4737","description":"Euro","rate_float":39063.4737},"CNY":{"code":"CNY","symbol":"&yen;","rate":"40,202.5000","description":"Chinese Yuan","rate_float":40202.5}}}