{"time":{"updated":"May 25, 2024 16:42:38 UTC","updatedISO":"2024-05-25T16:42:38+00:00","updateduk":"May 25, 2024 at 17:42 BST"},"disclaimer":"This data was produced from the CoinDesk Bitcoin Price Index (USD). Non-USD currency data converted using hourly conversion rate from openexchangerates.org","chartName":"Bitcoin","bpi":{"USD":{"code":"USD","symbol":"&#36;","rate":"69,000.784","description":"United States Dollar","rate_float":69000.7837},"GBP":{"code":"GBP","symbol":"&pound;","rate":"54,152.229","description":"British Pound Sterling","rate_float":54152.2291},"EUR":{"code":"EUR","symbol":"&euro;","rate":"63,603.956","description":"Euro","rate_float":63603.9564},"CNY":{"code":"CNY","symbol":"&yen;","rate":"490,630.073","description":"Chinese Yuan","rate_float":490630.0727}}}