{"time":{"updated":"Jul 7, 2022 23:26:00 UTC","updatedISO":"2022-07-07T23:26:00+00:00","updateduk":"Jul 8, 2022 at 00:26 BST"},"disclaimer":"This data was produced from the CoinDesk Bitcoin Price Index (USD). Non-USD currency data converted using hourly conversion rate from openexchangerates.org","chartName":"Bitcoin","bpi":{"USD":{"code":"USD","symbol":"&#36;","rate":"21,669.7422","description":"United States Dollar","rate_float":21669.7422},"GBP":{"code":"GBP","symbol":"&pound;","rate":"18,107.0632","description":"British Pound Sterling","rate_float":18107.0632},"EUR":{"code":"EUR","symbol":"&euro;","rate":"21,109.4927","description":"Euro","rate_float":21109.4927},"CNY":{"code":"CNY","symbol":"&yen;","rate":"40,202.5000","description":"Chinese Yuan","rate_float":40202.5}}}