{"time":{"updated":"Jan 31, 2024 23:01:46 UTC","updatedISO":"2024-01-31T23:01:46+00:00","updateduk":"Jan 31, 2024 at 23:01 GMT"},"disclaimer":"This data was produced from the CoinDesk Bitcoin Price Index (USD). Non-USD currency data converted using hourly conversion rate from openexchangerates.org","chartName":"Bitcoin","bpi":{"USD":{"code":"USD","symbol":"&#36;","rate":"42,635.233","description":"United States Dollar","rate_float":42635.2329},"GBP":{"code":"GBP","symbol":"&pound;","rate":"33,603.982","description":"British Pound Sterling","rate_float":33603.9821},"EUR":{"code":"EUR","symbol":"&euro;","rate":"39,410.858","description":"Euro","rate_float":39410.8582},"CNY":{"code":"CNY","symbol":"&yen;","rate":"302,688.836","description":"Chinese Yuan","rate_float":302688.8361}}}