{"time":{"updated":"Jul 4, 2024 12:08:27 UTC","updatedISO":"2024-07-04T12:08:27+00:00","updateduk":"Jul 4, 2024 at 13:08 BST"},"disclaimer":"This data was produced from the CoinDesk Bitcoin Price Index (USD). Non-USD currency data converted using hourly conversion rate from openexchangerates.org","chartName":"Bitcoin","bpi":{"USD":{"code":"USD","symbol":"&#36;","rate":"57,652.404","description":"United States Dollar","rate_float":57652.4038},"GBP":{"code":"GBP","symbol":"&pound;","rate":"45,192.105","description":"British Pound Sterling","rate_float":45192.1051},"EUR":{"code":"EUR","symbol":"&euro;","rate":"53,374.941","description":"Euro","rate_float":53374.9414},"CNY":{"code":"CNY","symbol":"&yen;","rate":"419,156.037","description":"Chinese Yuan","rate_float":419156.0369}}}