{"time":{"updated":"Jul 10, 2024 19:42:26 UTC","updatedISO":"2024-07-10T19:42:26+00:00","updateduk":"Jul 10, 2024 at 20:42 BST"},"disclaimer":"This data was produced from the CoinDesk Bitcoin Price Index (USD). Non-USD currency data converted using hourly conversion rate from openexchangerates.org","chartName":"Bitcoin","bpi":{"USD":{"code":"USD","symbol":"&#36;","rate":"57,538.998","description":"United States Dollar","rate_float":57538.9984},"GBP":{"code":"GBP","symbol":"&pound;","rate":"44,791.694","description":"British Pound Sterling","rate_float":44791.6936},"EUR":{"code":"EUR","symbol":"&euro;","rate":"53,154.297","description":"Euro","rate_float":53154.2966},"CNY":{"code":"CNY","symbol":"&yen;","rate":"418,659.507","description":"Chinese Yuan","rate_float":418659.5065}}}