{"time":{"updated":"Dec 4, 2024 08:45:43 UTC","updatedISO":"2024-12-04T08:45:43+00:00","updateduk":"Dec 4, 2024 at 08:45 GMT"},"disclaimer":"This data was produced from the CoinDesk Bitcoin Price Index (USD). Non-USD currency data converted using hourly conversion rate from openexchangerates.org","chartName":"Bitcoin","bpi":{"USD":{"code":"USD","symbol":"&#36;","rate":"96,871.32","description":"United States Dollar","rate_float":96871.3201},"GBP":{"code":"GBP","symbol":"&pound;","rate":"76,389.914","description":"British Pound Sterling","rate_float":76389.9137},"EUR":{"code":"EUR","symbol":"&euro;","rate":"92,179.358","description":"Euro","rate_float":92179.3577},"CNY":{"code":"CNY","symbol":"&yen;","rate":"704,535.424","description":"Chinese Yuan","rate_float":704535.4238}}}