{"time":{"updated":"Apr 29, 2024 15:47:18 UTC","updatedISO":"2024-04-29T15:47:18+00:00","updateduk":"Apr 29, 2024 at 16:47 BST"},"disclaimer":"This data was produced from the CoinDesk Bitcoin Price Index (USD). Non-USD currency data converted using hourly conversion rate from openexchangerates.org","chartName":"Bitcoin","bpi":{"USD":{"code":"USD","symbol":"&#36;","rate":"63,016.058","description":"United States Dollar","rate_float":63016.058},"GBP":{"code":"GBP","symbol":"&pound;","rate":"50,219.261","description":"British Pound Sterling","rate_float":50219.2611},"EUR":{"code":"EUR","symbol":"&euro;","rate":"58,822.213","description":"Euro","rate_float":58822.2133},"CNY":{"code":"CNY","symbol":"&yen;","rate":"456,292.974","description":"Chinese Yuan","rate_float":456292.9744}}}