{"time":{"updated":"Mar 22, 2024 06:52:29 UTC","updatedISO":"2024-03-22T06:52:29+00:00","updateduk":"Mar 22, 2024 at 06:52 GMT"},"disclaimer":"This data was produced from the CoinDesk Bitcoin Price Index (USD). Non-USD currency data converted using hourly conversion rate from openexchangerates.org","chartName":"Bitcoin","bpi":{"USD":{"code":"USD","symbol":"&#36;","rate":"66,466.365","description":"United States Dollar","rate_float":66466.3649},"GBP":{"code":"GBP","symbol":"&pound;","rate":"52,575.892","description":"British Pound Sterling","rate_float":52575.8916},"EUR":{"code":"EUR","symbol":"&euro;","rate":"61,311.433","description":"Euro","rate_float":61311.433},"CNY":{"code":"CNY","symbol":"&yen;","rate":"480,259.366","description":"Chinese Yuan","rate_float":480259.3661}}}