{"time":{"updated":"Dec 19, 2024 19:55:18 UTC","updatedISO":"2024-12-19T19:55:18+00:00","updateduk":"Dec 19, 2024 at 19:55 GMT"},"disclaimer":"This data was produced from the CoinDesk Bitcoin Price Index (USD). Non-USD currency data converted using hourly conversion rate from openexchangerates.org","chartName":"Bitcoin","bpi":{"USD":{"code":"USD","symbol":"&#36;","rate":"97,904.655","description":"United States Dollar","rate_float":97904.655},"GBP":{"code":"GBP","symbol":"&pound;","rate":"76,607.749","description":"British Pound Sterling","rate_float":76607.7491},"EUR":{"code":"EUR","symbol":"&euro;","rate":"92,965.365","description":"Euro","rate_float":92965.3651},"CNY":{"code":"CNY","symbol":"&yen;","rate":"709,779.377","description":"Chinese Yuan","rate_float":709779.3772}}}