{"time":{"updated":"Jan 26, 2025 19:18:04 UTC","updatedISO":"2025-01-26T19:18:04+00:00","updateduk":"Jan 26, 2025 at 19:18 GMT"},"disclaimer":"This data was produced from the CoinDesk Bitcoin Price Index (USD). Non-USD currency data converted using hourly conversion rate from openexchangerates.org","chartName":"Bitcoin","bpi":{"USD":{"code":"USD","symbol":"&#36;","rate":"104,283.342","description":"United States Dollar","rate_float":104283.3423},"GBP":{"code":"GBP","symbol":"&pound;","rate":"83,173.787","description":"British Pound Sterling","rate_float":83173.7867},"EUR":{"code":"EUR","symbol":"&euro;","rate":"100,292.836","description":"Euro","rate_float":100292.8359},"CNY":{"code":"CNY","symbol":"&yen;","rate":"764,177.904","description":"Chinese Yuan","rate_float":764177.9039}}}