{"time":{"updated":"Jan 27, 2022 17:45:00 UTC","updatedISO":"2022-01-27T17:45:00+00:00","updateduk":"Jan 27, 2022 at 17:45 GMT"},"disclaimer":"This data was produced from the CoinDesk Bitcoin Price Index (USD). Non-USD currency data converted using hourly conversion rate from openexchangerates.org","chartName":"Bitcoin","bpi":{"USD":{"code":"USD","symbol":"&#36;","rate":"36,242.1317","description":"United States Dollar","rate_float":36242.1317},"GBP":{"code":"GBP","symbol":"&pound;","rate":"27,076.6778","description":"British Pound Sterling","rate_float":27076.6778},"EUR":{"code":"EUR","symbol":"&euro;","rate":"32,526.4796","description":"Euro","rate_float":32526.4796},"CNY":{"code":"CNY","symbol":"&yen;","rate":"40,202.5000","description":"Chinese Yuan","rate_float":40202.5}}}